{
  "seo": {
    "title": "Home",
    "description": "Tina is a content management platform, with a content management API and frontend toolkit to rapidly prototype your own CMS."
  },
  "blocks": [
    {
      "_template": "navbar",
      "banner": {
        "display": false,
        "text": "",
        "link": ""
      },
      "navItems": [
        {
          "link": "/docs",
          "label": "Docs"
        },
        {
          "link": "/guides",
          "label": "Guides"
        },
        {
          "link": "/blog",
          "label": "Blog"
        }
      ]
    },
    {
      "_template": "hero",
      "headline": "Unlock your content team with next-gen editing",
      "subline": "Tina is an open-source content editing UI for the JAMstack",
      "actions": [
        {
          "variant": "orange",
          "label": "Try Demo",
          "icon": "arrowRight",
          "url": "#"
        },
        {
          "variant": "ghost",
          "label": "Read Docs",
          "icon": "",
          "url": "#"
        }
      ],
      "videoSrc": "v1571425758/tina-hero-demo-v2"
    },
    {
      "_template": "features",
      "headline": "",
      "subline": "",
      "items": [
        {
          "_template": "feature",
          "headline": "Plugin Into Any Data Source, Edit with Tina",
          "subline": "Tina can connect to any API that stores content such as GitHub, a headless CMS, 3rd-party APIs, or even the file system.",
          "media": {
            "src": "/img/connect-to-api.png"
          }
        },
        {
          "_template": "feature",
          "headline": "Visual Editing",
          "subline": "Most CMSs feel like GUI on a database. Tina gives your team a contextual, intuitive experience.",
          "media": {
            "src": "/img/io-placeholder.jpg"
          }
        },
        {
          "_template": "feature",
          "headline": "Built for the JAMstack",
          "subline": "Tina is designed for the JAMstack and currently works for React-based sites",
          "media": {
            "src": "/img/jamstack.png"
          }
        },
        {
          "_template": "feature",
          "headline": "Integrate Your Design Systems",
          "subline": "Allow your team to pick from your custom, predefined components to build pages.",
          "media": {
            "src": "/img/design-system.png"
          }
        }
      ]
    },
    {
      "_template": "browser",
      "headline": "*Avoid Vendor Lock-In*",
      "subline": "",
      "browser": {
        "headline": "Edit with Tina",
        "subline": "Write to your content/data",
        "text": "Connect to the single source of truth for you data",
        "media": {
          "src": "/img/blocks.gif"
        }
      },
      "items": [
        {
          "headline": "Headless CMSs",
          "subline": "Connect to a headless CMS for a better content editing experience",
          "icon": "arrowRight",
          "media": {
            "src": "img/headlessCms.png"
          }
        },
        {
          "headline": "Git Repo",
          "subline": "Connect to the GitHub API with the Tina GitHub pluing",
          "icon": "arrowRight",
          "media": {
            "src": "img/git-providers.png"
          }
        },
        {
          "headline": "3rd Party API",
          "subline": "Store your content in Airtable, Google Sheets, or any data source",
          "icon": "arrowRight",
          "media": {
            "src": "img/headlessCms.png"
          }
        }
      ]
    },
    {
      "_template": "flying",
      "headline": "Learn Tina",
      "subline": "Learn Tina through Interactive & Fun Tutorials.",
      "actions": [
        {
          "variant": "orange",
          "label": "Get Started",
          "icon": "arrowRight",
          "url": "#"
        }
      ]
    }
  ]
}