{
  "versionNumber": "2025.01.63",
  "dateReleased": "2025-01-02T00:26:35Z",
  "changesObject": [
    {
      "changesTitle": "✨ Features",
      "changesList": [
        {
          "changesDescription": "feat: logging for external user invitations",
          "gitHubName": "kldavis4",
          "gitHubLink": "https://github.com/kldavis4"
        }
      ]
    },
    {
      "changesTitle": "🔧 Fixes",
      "changesList": [
        {
          "changesDescription": "📝 README - Corrects TinaCloud mentions, updates SST mentions",
          "gitHubName": "ncn-ssw",
          "gitHubLink": "https://github.com/ncn-ssw"
        },
        {
          "changesDescription": "fix: sanitize release notes by removing links and HTML comments",
          "gitHubName": "wicksipedia",
          "gitHubLink": "https://github.com/wicksipedia"
        }
      ]
    }
  ]
}
